jmq_chirpstack/__init__.py
jmq_chirpstack/chirpstack_api.py
jmq_chirpstack-0.1.0.dist-info/licenses/LICENSE
jmq_chirpstack-0.1.0.dist-info/METADATA
jmq_chirpstack-0.1.0.dist-info/WHEEL
jmq_chirpstack-0.1.0.dist-info/top_level.txt
jmq_chirpstack-0.1.0.dist-info/RECORD
