Metadata-Version: 2.4
Name: jmq_chirpstack
Version: 0.1.0
Summary: Paquete de Integración Chirpstack con Python
Author-email: Juanma Quijada <quijada.jm@gmail.com>
License: MIT
Project-URL: Homepage, https://github.com/juaquicar/jmq_chirpstack
Classifier: Programming Language :: Python :: 3
Classifier: License :: OSI Approved :: MIT License
Classifier: Operating System :: OS Independent
Requires-Python: >=3.6
License-File: LICENSE
Dynamic: license-file
